crypto_monitor/__init__.py
crypto_monitor/binance.py
crypto_monitor/utils.py
crypto_monitor-0.2.3.dist-info/METADATA
crypto_monitor-0.2.3.dist-info/WHEEL
crypto_monitor-0.2.3.dist-info/top_level.txt
crypto_monitor-0.2.3.dist-info/RECORD
