Metadata-Version: 2.4
Name: crypto-monitor
Version: 0.2.3
Summary: Lightweight real-time cryptocurrency market monitor via WebSocket
Home-page: https://github.com/SerenaTradingResearch/crypto-monitor
Author: Ricky Ding
Author-email: e0134117@u.nus.edu
License: MIT
Keywords: crypto,binance,websocket,realtime,market-data,monitor
Classifier: Programming Language :: Python :: 3
Classifier: Intended Audience :: Financial and Insurance Industry
Classifier: License :: OSI Approved :: MIT License
Requires-Python: >=3.8
Requires-Dist: crypto-data-downloader
Requires-Dist: Pillow
Dynamic: author
Dynamic: author-email
Dynamic: classifier
Dynamic: description
Dynamic: description-content-type
Dynamic: home-page
Dynamic: keywords
Dynamic: license
Dynamic: requires-dist
Dynamic: requires-python
Dynamic: summary
